CONTRIBUTING.rst
COPYING
LICENSE
MANIFEST.in
README.rst
setup.py
docs/Makefile
docs/conf.py
docs/index.rst
docs/installation.rst
docs/tests.rst
docs/usage.rst
hbx_django_tastypie_mongoengine.egg-info/PKG-INFO
hbx_django_tastypie_mongoengine.egg-info/SOURCES.txt
hbx_django_tastypie_mongoengine.egg-info/dependency_links.txt
hbx_django_tastypie_mongoengine.egg-info/not-zip-safe
hbx_django_tastypie_mongoengine.egg-info/requires.txt
hbx_django_tastypie_mongoengine.egg-info/top_level.txt
tastypie_mongoengine/__init__.py
tastypie_mongoengine/fields.py
tastypie_mongoengine/paginator.py
tastypie_mongoengine/resources.py
tastypie_mongoengine/test_runner.py
tests/__init__.py
tests/manage.py
tests/runtests.py
tests/test_project/__init__.py
tests/test_project/settings.py
tests/test_project/urls.py
tests/test_project/test_app/__init__.py
tests/test_project/test_app/documents.py
tests/test_project/test_app/models.py
tests/test_project/test_app/views.py
tests/test_project/test_app/api/__init__.py
tests/test_project/test_app/api/resources.py
tests/test_project/test_app/tests/__init__.py
tests/test_project/test_app/tests/test_basic.py