Metadata-Version: 1.1
Name: hbx-django-tastypie-mongoengine
Version: 0.4.6
Summary: MongoEngine support for django-tastypie. Fixed for Django 1.9+
Home-page: https://github.com/wlanslovenija/django-tastypie-mongoengine
Author: wlan slovenija
Author-email: open@wlan-si.net
License: AGPLv3
Keywords: REST RESTful tastypie mongo mongodb mongoengine django
Platform: UNKNOWN
Classifier: Development Status :: 4 - Beta
Classifier: Environment :: Web Environment
Classifier: Intended Audience :: Developers
Classifier: License :: OSI Approved :: GNU Affero General Public License v3
Classifier: Operating System :: OS Independent
Classifier: Programming Language :: Python
Classifier: Framework :: Django
